benchmarks/__init__.py
benchmarks/benchmarks.py
enlighten/__init__.py
enlighten/_basecounter.py
enlighten/_basemanager.py
enlighten/_counter.py
enlighten/_manager.py
enlighten/_notebook_manager.py
enlighten/_statusbar.py
enlighten/_util.py
enlighten/counter.py
enlighten/manager.py
enlighten-1.14.0.dist-info/LICENSE
enlighten-1.14.0.dist-info/METADATA
enlighten-1.14.0.dist-info/WHEEL
enlighten-1.14.0.dist-info/top_level.txt
enlighten-1.14.0.dist-info/RECORD
