Metadata-Version: 2.2
Name: enlighten
Version: 1.14.0
Summary: Enlighten Progress Bar
Home-page: https://github.com/Rockhopper-Technologies/enlighten
Author: Avram Lubkin
Author-email: avylove@rockhopper.net
Maintainer: Avram Lubkin
Maintainer-email: avylove@rockhopper.net
License: MPLv2.0
Project-URL: Documentation, https://python-enlighten.readthedocs.io
Keywords: progress,bar,progressbar,counter,status,statusbar
Classifier: Development Status :: 5 - Production/Stable
Classifier: Environment :: Console
Classifier: Intended Audience :: Developers
Classifier: License :: OSI Approved :: Mozilla Public License 2.0 (MPL 2.0)
Classifier: Operating System :: POSIX
Classifier: Operating System :: Microsoft :: Windows
Classifier: Programming Language :: Python
Classifier: Programming Language :: Python :: 2.7
Classifier: Programming Language :: Python :: 3.5
Classifier: Programming Language :: Python :: 3.6
Classifier: Programming Language :: Python :: 3.7
Classifier: Programming Language :: Python :: 3.8
Classifier: Programming Language :: Python :: 3.9
Classifier: Programming Language :: Python :: 3.10
Classifier: Programming Language :: Python :: 3.11
Classifier: Programming Language :: Python :: 3.12
Classifier: Programming Language :: Python :: 3.13
Classifier: Programming Language :: Python :: Implementation :: CPython
Classifier: Programming Language :: Python :: Implementation :: PyPy
Classifier: Topic :: Utilities
License-File: LICENSE
Requires-Dist: blessed>=1.17.7
Requires-Dist: prefixed>=0.3.2
Requires-Dist: backports.functools-lru-cache; python_version < "3.2"
Dynamic: author
Dynamic: author-email
Dynamic: classifier
Dynamic: description
Dynamic: home-page
Dynamic: keywords
Dynamic: license
Dynamic: maintainer
Dynamic: maintainer-email
Dynamic: project-url
Dynamic: requires-dist
Dynamic: summary
